setup.cfg
setup.py
Tweet_Lake.egg-info/PKG-INFO
Tweet_Lake.egg-info/SOURCES.txt
Tweet_Lake.egg-info/dependency_links.txt
Tweet_Lake.egg-info/entry_points.txt
Tweet_Lake.egg-info/requires.txt
Tweet_Lake.egg-info/top_level.txt
tweetlake/__init__.py
tweetlake/config.py
tweetlake/console/__init__.py
tweetlake/console/tl.py
tweetlake/stream/__init__.py
tweetlake/stream/stream_listeners.py
tweetlake/utils/__init__.py
tweetlake/utils/filters.py
tweetlake/utils/processors.py
tweetlake/utils/sinks.py