Metadata-Version: 1.1
Name: Tweet-Lake
Version: 0.1.dev2
Summary: Tweet Lake is a commandline interface to Twitter Streaming API and big data project that extracts interesting stats out of tweet corpus.
Home-page: https://harshulja.in/projects/tweet-lake/
Author: Harshul Jain
Author-email: harshulj@gmail.com
License: MIT
Download-URL: https://github.com/harshulj/tweetlake/tarball/0.1.dev1
Keywords: twitter,streaming,api,tweepy,commandline
Platform: UNKNOWN
